ocp/__init__.py
ocp/ocp_linux_amd64
ocp_linux_amd64-0.1.8.dist-info/LICENSE
ocp_linux_amd64-0.1.8.dist-info/METADATA
ocp_linux_amd64-0.1.8.dist-info/WHEEL
ocp_linux_amd64-0.1.8.dist-info/top_level.txt
ocp_linux_amd64-0.1.8.dist-info/RECORD
