Metadata-Version: 2.1
Name: ocp-linux-amd64
Version: 0.1.8
Summary: Open Collaboration Platform binary node package
Home-page: https://github.com/OpenCollaborationPlatform
Author: Stefan Tröger
Author-email: stefantroeger@gmx.net
Maintainer: Stefan Tröger
Maintainer-email: stefantroeger@gmx.net
License: LGPL2.1+
Download-URL: https://github.com/OpenCollaborationPlatform/PythonOCP
Platform: linux
License-File: LICENSE
